{
    "navigate": [
        {
            "pic": "",
            "desc": "I18N=TIANYU_NATIVE_PROJECT",
            "key": "tianyu-native",
            "sub": [
                {
                    "desc": "I18N=TIANYU_NATIVE_PROJECT_HELP",
                    "key": "help"
                },
                {
                    "desc": "I18N=TIANYU_NATIVE_PROJECT_DEV",
                    "key": "develop",
                    "sub": [
                        {
                            "desc": "I18N=TIANYU_NATIVE_PROJECT_MACRO",
                            "key": "macro"
                        },
                        {
                            "desc": "I18N=TIANYU_NATIVE_PROJECT_INTERNATION",
                            "key": "i18n"
                        },
                        {
                            "desc": "I18N=TIANYU_NATIVE_PROJECT_DATA_TYPE",
                            "key": "model"
                        },
                        {
                            "desc": "I18N=TIANYU_NATIVE_PROJECT_NAMESPACE",
                            "key": "namespace"
                        }
                    ]
                }
            ]
        }
    ]
}
